gaea_metric/__init__.py
gaea_metric/cli.py
gaea_metric/metric.py
gaea_metric/misc.py
gaea_metric/module.py
gaea_metric/plugin.py
gaea_metric/registry.py
gaea_metric/image/__init__.py
gaea_metric/image/accuracy.py
gaea_metric/image/average_precision.py
gaea_metric/image/confusion_matrix.py
gaea_metric/image/mean_ap.py
gaea_metric/image/mean_iou.py
gaea_metric/image/precision_recall_curve.py
gaea_metric/image/precision_recall_f1score.py
gaea_operator/__init__.py
gaea_operator/cli.py
gaea_operator/plugin.py
gaea_operator/trainer.py
gaea_operator/data/__init__.py
gaea_operator/data/dali_dataloader.py
gaea_operator/data/paddle_dataloader.py
gaea_operator/data/random_split.py
gaea_operator/data/process/__init__.py
gaea_operator/data/process/anno_parse.py
gaea_operator/data/process/convert.py
gaea_operator/data/source/__init__.py
gaea_operator/data/source/anno_parse.py
gaea_operator/data/source/base.py
gaea_operator/data/source/dali_dataset.py
gaea_operator/data/source/dataset.py
gaea_operator/data/transforms/__init__.py
gaea_operator/data/transforms/dali_ops.py
gaea_operator/data/transforms/paddle_fns.py
gaea_operator/data/transforms/paddle_ops.py
gaea_operator/distributed/__init__.py
gaea_operator/distributed/accelerator.py
gaea_operator/distributed/launcher.py
gaea_operator/distributed/utils.py
gaea_operator/distributed/comp_models/__init__.py
gaea_operator/distributed/comp_models/base.py
gaea_operator/distributed/comp_models/horovod_dist.py
gaea_operator/distributed/comp_models/paddle_dist.py
gaea_operator/distributed/comp_models/torch_dist.py
gaea_operator/engine/__init__.py
gaea_operator/engine/engine.py
gaea_operator/engine/events.py
gaea_operator/engine/mixins.py
gaea_operator/engine/utils.py
gaea_operator/handlers/__init__.py
gaea_operator/handlers/checkpoint.py
gaea_operator/handlers/early_stop.py
gaea_operator/handlers/metric_logger.py
gaea_operator/handlers/model_ema.py
gaea_operator/handlers/profiler.py
gaea_operator/handlers/store.py
gaea_metric-1.1.1.dist-info/METADATA
gaea_metric-1.1.1.dist-info/WHEEL
gaea_metric-1.1.1.dist-info/top_level.txt
gaea_metric-1.1.1.dist-info/RECORD
