Metadata-Version: 2.1
Name: gaea-metric
Version: 1.1.1
Summary: A common metric library.
Home-page: https://console.cloud.baidu-int.com/devops/icode/repos/baidu/mlops/gaea-operator/tree/master
Author: liuyawen03
Author-email: liuyawen03@baidu.com
License: MIT
Classifier: Programming Language :: Python
Classifier: Programming Language :: Python :: 3
Classifier: Programming Language :: Python :: 3.7
Classifier: Programming Language :: Python :: 3.8
Classifier: Programming Language :: Python :: 3.9
Requires-Python: >=3.6
Requires-Dist: numpy (==1.22)
Requires-Dist: astor (>=0.8.1)
Requires-Dist: certifi (>=2022.9.14)
Requires-Dist: charset-normalizer (>=2.1.1)
Requires-Dist: debugpy (>=1.6.3)
Requires-Dist: decorator (>=5.1.1)
Requires-Dist: idna (>=3.4)
Requires-Dist: opt-einsum (>=3.3.0)
Requires-Dist: protobuf (>=3.20.0)
Requires-Dist: PyYAML (>=6.0)
Requires-Dist: six (>=1.16.0)
Requires-Dist: urllib3 (>=1.26.12)
Requires-Dist: pycocotools (>=2.0.6)
Requires-Dist: jsonargparse (==4.20.0)
Requires-Dist: paddlepaddle (==2.4.2)
Requires-Dist: torch (==1.12.0)
